[{"Issue Name":"Tensorflow Training crashes when using tf dataset on large amount of data","Issue Link":"https://www.github.com/tensorflow/tensorflow/issues/47916"},{"Issue Name":"Build fails on Arch Linux","Issue Link":"https://www.github.com/tensorflow/tensorflow/issues/47915"},{"Issue Name":"Tenorflow Traceback Errors","Issue Link":"https://www.github.com/tensorflow/tensorflow/issues/47913"},{"Issue Name":"Weights in tf.estimator.BoostedTreesClassifier()","Issue Link":"https://www.github.com/tensorflow/tensorflow/issues/47912"},{"Issue Name":"Tracking python lists (or ListWrapper) in keras custom preprocessing layers","Issue Link":"https://www.github.com/tensorflow/tensorflow/issues/47910"},{"Issue Name":"TF.keras in TF2.4","Issue Link":"https://www.github.com/tensorflow/tensorflow/issues/47909"},{"Issue Name":"TF2 + GH","Issue Link":"https://www.github.com/tensorflow/tensorflow/issues/47908"},{"Issue Name":"Using custom callback to set trainable=true doesn't work when use model.fit()","Issue Link":"https://www.github.com/tensorflow/tensorflow/issues/47906"},{"Issue Name":"tflite runtime API + NNAPI delegate refusing layers from a MobileNetV2SSD trained with Object Detection API, with high inference time","Issue Link":"https://www.github.com/tensorflow/tensorflow/issues/47905"},{"Issue Name":"ASL Gesture Recognition SSD Model not showing labels upon running","Issue Link":"https://www.github.com/tensorflow/tensorflow/issues/47904"},{"Issue Name":"Train.py error Blas GEMM launch failed","Issue Link":"https://www.github.com/tensorflow/tensorflow/issues/47903"},{"Issue Name":"Unable to link c++ project due to missing header files","Issue Link":"https://www.github.com/tensorflow/tensorflow/issues/47902"},{"Issue Name":"Feature Request for N-Dimensional Operations","Issue Link":"https://www.github.com/tensorflow/tensorflow/issues/47901"},{"Issue Name":"WARNING:tensorflow:AutoGraph could not transform <bound method Socket.send of <zmq.sugar.socket.Socket object at 0x7f817468a4c0>> and will run it as-is","Issue Link":"https://www.github.com/tensorflow/tensorflow/issues/47898"},{"Issue Name":"using ragged tensors with custom loss and metric","Issue Link":"https://www.github.com/tensorflow/tensorflow/issues/47895"},{"Issue Name":"TFLite Documentation Request: How do per-axis quantizations work with subsequent layers?","Issue Link":"https://www.github.com/tensorflow/tensorflow/issues/47893"},{"Issue Name":"OSError: Cannot understand given URI: <tf.Tensor 'filepath:0' shape=() dtype=string>.","Issue Link":"https://www.github.com/tensorflow/tensorflow/issues/47891"},{"Issue Name":"Latest Windows 10 update - Import tensorflow - Kernel dies","Issue Link":"https://www.github.com/tensorflow/tensorflow/issues/47890"},{"Issue Name":"Rename tf.keras.optimizers to tf.keras.optims for more aesthetic import statements","Issue Link":"https://www.github.com/tensorflow/tensorflow/issues/47889"},{"Issue Name":"Tensorflow lite micro 2.4 Alpha version missing tflite::ops::micro::Register_FULLY_CONNECTED()","Issue Link":"https://www.github.com/tensorflow/tensorflow/issues/47888"},{"Issue Name":"Segmentation Fault when Benchmarking TFLite EfficientNetB0","Issue Link":"https://www.github.com/tensorflow/tensorflow/issues/47886"},{"Issue Name":"Return gradient 0 in mixed_precison setting","Issue Link":"https://www.github.com/tensorflow/tensorflow/issues/47884"},{"Issue Name":"Unable to install Tensorflow due to one of the file named \"getObjectTorrentRequest.h\" file , Torrent named file are blocked in various system across organisations.","Issue Link":"https://www.github.com/tensorflow/tensorflow/issues/47883"},{"Issue Name":"How Is Padding Calculated for Conv1D,2D,....","Issue Link":"https://www.github.com/tensorflow/tensorflow/issues/47882"}]